adcp_recorder/__init__.py
adcp_recorder/config.py
adcp_recorder/api/main.py
adcp_recorder/cli/__init__.py
adcp_recorder/cli/main.py
adcp_recorder/core/__init__.py
adcp_recorder/core/enums.py
adcp_recorder/core/nmea.py
adcp_recorder/core/recorder.py
adcp_recorder/db/__init__.py
adcp_recorder/db/db.py
adcp_recorder/db/migration.py
adcp_recorder/db/models.py
adcp_recorder/db/operations.py
adcp_recorder/db/schema.py
adcp_recorder/export/binary_writer.py
adcp_recorder/export/bulk_export.py
adcp_recorder/export/file_writer.py
adcp_recorder/export/parquet_writer.py
adcp_recorder/parsers/__init__.py
adcp_recorder/parsers/pnora.py
adcp_recorder/parsers/pnorb.py
adcp_recorder/parsers/pnorc.py
adcp_recorder/parsers/pnore.py
adcp_recorder/parsers/pnorf.py
adcp_recorder/parsers/pnorh.py
adcp_recorder/parsers/pnori.py
adcp_recorder/parsers/pnors.py
adcp_recorder/parsers/pnorw.py
adcp_recorder/parsers/pnorwd.py
adcp_recorder/parsers/utils.py
adcp_recorder/serial/__init__.py
adcp_recorder/serial/binary_chunk.py
adcp_recorder/serial/consumer.py
adcp_recorder/serial/port_manager.py
adcp_recorder/serial/producer.py
adcp_recorder/service/supervisor.py
adcp_recorder/templates/__init__.py
adcp_recorder/templates/linux/adcp-recorder.service
adcp_recorder/templates/windows/install-service-windows.ps1
adcp_recorder/ui/config.py
adcp_recorder/ui/dashboard.py
adcp_recorder/ui/data_layer.py
adcp_recorder/ui/parquet_data_layer.py
adcp_recorder/ui/components/__init__.py
adcp_recorder/ui/components/file_browser.py
adcp_recorder/ui/components/spectrum_plots.py
adcp_recorder/ui/components/table_view.py
adcp_recorder/ui/components/time_series.py
adcp_recorder/ui/components/velocity_profile.py
adcp_recorder/ui/pages/__init__.py
adcp_recorder/ui/pages/dashboard_editor.py
adcp_recorder/ui/pages/data_explorer.py
adcp_recorder/ui/pages/plot_builder.py
adcp_recorder-0.2.1.dist-info/licenses/LICENSE
adcp_recorder-0.2.1.dist-info/METADATA
adcp_recorder-0.2.1.dist-info/WHEEL
adcp_recorder-0.2.1.dist-info/entry_points.txt
adcp_recorder-0.2.1.dist-info/top_level.txt
adcp_recorder-0.2.1.dist-info/RECORD
