Metadata-Version: 2.4
Name: adcp-recorder
Version: 0.2.1
Summary: NMEA telemetry recorder for Nortek ADCP instruments with DuckDB backend
Author-email: V P <vp@avp-systeme.de>
Maintainer-email: V P <vp@avp-systeme.de>
License: MIT
Project-URL: Homepage, https://github.com/vpatrinica/adcp-recorder
Project-URL: Documentation, https://github.com/vpatrinica/adcp-recorder/tree/main/docs
Project-URL: Repository, https://github.com/vpatrinica/adcp-recorder
Project-URL: Issues, https://github.com/vpatrinica/adcp-recorder/issues
Project-URL: Changelog, https://github.com/vpatrinica/adcp-recorder/blob/main/CHANGELOG.md
Keywords: adcp,nmea,telemetry,oceanography,marine,data-acquisition,nortek,duckdb,serial
Classifier: Development Status :: 4 - Beta
Classifier: Intended Audience :: Science/Research
Classifier: License :: OSI Approved :: MIT License
Classifier: Operating System :: OS Independent
Classifier: Operating System :: POSIX :: Linux
Classifier: Operating System :: Microsoft :: Windows
Classifier: Programming Language :: Python :: 3
Classifier: Programming Language :: Python :: 3.13
Classifier: Programming Language :: Python :: 3.14
Classifier: Topic :: Scientific/Engineering
Classifier: Topic :: Scientific/Engineering :: Oceanography
Classifier: Topic :: System :: Monitoring
Classifier: Topic :: Database
Requires-Python: >=3.13
License-File: LICENSE
Requires-Dist: pyserial>=3.5
Requires-Dist: duckdb>=0.9.0
Requires-Dist: click>=8.1.0
Requires-Dist: polars>=1.0.0
Requires-Dist: sqlmodel>=0.0.14
Requires-Dist: duckdb-engine>=0.9.2
Requires-Dist: numpy>=1.26.0
Provides-Extra: dev
Requires-Dist: pytest>=7.4.0; extra == "dev"
Requires-Dist: pytest-cov>=4.1.0; extra == "dev"
Requires-Dist: pytest-mock>=3.11.0; extra == "dev"
Requires-Dist: ruff>=0.1.0; extra == "dev"
Requires-Dist: types-pyserial>=3.5; extra == "dev"
Requires-Dist: mypy>=1.0.0; extra == "dev"
Provides-Extra: analysis
Requires-Dist: fastapi>=0.100.0; extra == "analysis"
Requires-Dist: uvicorn[standard]>=0.23.0; extra == "analysis"
Requires-Dist: streamlit>=1.30.0; extra == "analysis"
Requires-Dist: plotly>=5.18.0; extra == "analysis"
Requires-Dist: pydantic>=2.0.0; extra == "analysis"
Requires-Dist: pyyaml>=6.0.0; extra == "analysis"
Dynamic: license-file
